EzQmt/__init__.py
EzQmt/smy.py
EzQmt-2.1.0.dist-info/METADATA
EzQmt-2.1.0.dist-info/WHEEL
EzQmt-2.1.0.dist-info/top_level.txt
EzQmt-2.1.0.dist-info/RECORD
