Metadata-Version: 2.1
Name: EzQmt
Version: 2.1.0
Summary: Package for QMT
Home-page: https://github.com/LHanLi/EzQmt
Author: LH.Li
Author-email: lh98lee@zju.edu.cn
Classifier: Programming Language :: Python :: 3
Classifier: License :: OSI Approved :: GNU General Public License v3 or later (GPLv3+)
Classifier: Operating System :: OS Independent
